[
    {
        "content": "* Q3 earnings per share view $0.34 -- Thomson Reuters I/B/E/S",
        "date": "11012017",
        "name": "Flowserve Corporation",
        "news_type": "topStory",
        "symbol": "FLS",
        "title": "BRIEF-Flowserve Corp reports Q3 adjusted earnings per share $0.37 "
    },
    {
        "content": "* Flowserve announces the appointment of Lee Eckert as chief financial officer",
        "date": "09212017",
        "name": "Flowserve Corporation",
        "news_type": "topStory",
        "symbol": "FLS",
        "title": "BRIEF-Flowserve announces appointment of Lee Eckert as CFO "
    },
    {
        "content": "* Flowserve announces quarterly cash dividend of $0.19 per share Further company coverage: (Bengaluru Newsroom: +1 646 223 8780)",
        "date": "09062017",
        "name": "Flowserve Corporation",
        "news_type": "topStory",
        "symbol": "FLS",
        "title": "BRIEF-Flowserve announces quarterly cash dividend of $0.19 per share "
    },
    {
        "content": "* Flowserve Corp files for non-timely 10-Q - SEC filing Source text: (http://bit.ly/2vnUqN2) Further company coverage:",
        "date": "08092017",
        "name": "Flowserve Corporation",
        "news_type": "topStory",
        "symbol": "FLS",
        "title": "BRIEF-Flowserve Corp files for non-timely 10-Q - SEC Filing "
    },
    {
        "content": "* Flowserve Corp - \u200dbacklog at June 30  2017 was $2.1 billion  up 12.4% and 1.5% versus 2016 year-end  and prior year Q2  respectively\u200b",
        "date": "07272017",
        "name": "Flowserve Corporation",
        "news_type": "topStory",
        "symbol": "FLS",
        "title": "BRIEF-Flowserve Corporation qtrly \u200dadjusted EPS was $0.22 "
    },
    {
        "content": "* Flowserve Corp says on june 30 entered into a fourth amendment to its existing credit agreement  dated august 20  2012 - sec filing",
        "date": "07072017",
        "name": "Flowserve Corporation",
        "news_type": "topStory",
        "symbol": "FLS",
        "title": "BRIEF-Flowserve says on June 30 entered into fourth amendment to its existing credit agreement  dated August 20  2012 "
    },
    {
        "content": "* Board voted to amend co's bylaws  which reduces number of directors of company from 10 to 9 - SEC filing Source text for Eikon: Further company coverage:",
        "date": "05242017",
        "name": "Flowserve Corporation",
        "news_type": "topStory",
        "symbol": "FLS",
        "title": "BRIEF-Flowserve board votes to reduce number of directors of company from 10 to 9 "
    },
    {
        "content": "* Q1 earnings per share view $0.19 -- Thomson Reuters I/B/E/S",
        "date": "05012017",
        "name": "Flowserve Corporation",
        "news_type": "topStory",
        "symbol": "FLS",
        "title": "BRIEF-Flowserve Q1 earnings per share $0.11 "
    },
    {
        "content": "* Signed a conditional sale and purchase agreement to acquire Gestra AG and associated businesses from Flowserve Corporation",
        "date": "04032017",
        "name": "Flowserve Corporation",
        "news_type": "topStory",
        "symbol": "FLS",
        "title": "BRIEF-Spirax-Sarco to buy Flowserve Corp's Gestra for 186 million euros "
    },
    {
        "content": "* Flowserve appoints Jay Roueche interim chief financial officer",
        "date": "02242017",
        "name": "Flowserve Corporation",
        "news_type": "topStory",
        "symbol": "FLS",
        "title": "BRIEF-Flowserve appoints Jay Roueche interim CFO "
    },
    {
        "content": "* Flowserve Corporation reports fourth quarter and full year 2016 results; issues 2017 financial guidance",
        "date": "02162017",
        "name": "Flowserve Corporation",
        "news_type": "topStory",
        "symbol": "FLS",
        "title": "BRIEF-Flowserve reports Q4 earnings per share $0.50 "
    },
    {
        "content": "* Co's newly announced CEO R. Scott Rowe will receive an annual base salary of $1.1 million - SEC filing  Source text for Eikon: (http://bit.ly/2klRdri) Further company coverage:",
        "date": "02082017",
        "name": "Flowserve Corporation",
        "news_type": "topStory",
        "symbol": "FLS",
        "title": "BRIEF-Flowserve co's new CEO Scott Rowe to get annual base salary of $1.1 million "
    },
    {
        "content": "* Flowserve appoints R. Scott Rowe as president and chief executive officer",
        "date": "02082017",
        "name": "Flowserve Corporation",
        "news_type": "normal",
        "symbol": "FLS",
        "title": "BRIEF-Flowserve appoints R. Scott Rowe as chief executive officer "
    },
    {
        "content": "* Flowserve corp - remain on track to deliver expected incremental savings of approximately $100 million in 2016",
        "date": "10272016",
        "name": "Flowserve Corporation",
        "news_type": "topStory",
        "symbol": "FLS",
        "title": "BRIEF-Flowserve corporation reports Q3 loss per share $0.16 "
    },
    {
        "content": "* Honeywell and Flowserve collaborate on industrial internet of things (IIOT) solutions  Source text for Eikon:  Further company coverage:",
        "date": "10262016",
        "name": "Flowserve Corporation",
        "news_type": "topStory",
        "symbol": "FLS",
        "title": "BRIEF-Honeywell and Flowserve collaborate on industrial internet of things solutions "
    },
    {
        "content": "* Q1 earnings per share view $0.42 -- Thomson Reuters I/B/E/S",
        "date": "04282016",
        "name": "Flowserve Corporation",
        "news_type": "topStory",
        "symbol": "FLS",
        "title": "BRIEF-Flowserve Corp Q1 earnings per share $0.29 "
    },
    {
        "content": "* Files for mixed shelf offering; size undisclosed - SEC filing  Source text http://1.usa.gov/1M7sZxn Further company coverage:",
        "date": "04012016",
        "name": "Flowserve Corporation",
        "news_type": "topStory",
        "symbol": "FLS",
        "title": "BRIEF-Flowserve files for mixed shelf offering; size undisclosed - SEC filing "
    },
    {
        "content": "* Trian takes 7.2 pct stake; is Pentair's 3rd-biggest shareholder",
        "date": "06302015",
        "name": "Flowserve Corporation",
        "news_type": "topStory",
        "symbol": "FLS",
        "title": "UPDATE 2-Peltz takes stake in Pentair  asks company to bulk up "
    }
]