[
    {
        "content": "* Kirby corp - expect q4 utilization in low 60% to mid-60% range for costal markets",
        "date": "11012017",
        "name": "Kirby Corporation",
        "news_type": "topStory",
        "symbol": "KEX",
        "title": "BRIEF--Kirby Corp Q3 earnings per share $0.52 "
    },
    {
        "content": "* Q3 revenue $541.3 million versus I/B/E/S view $509.5 million",
        "date": "11012017",
        "name": "Kirby Corporation",
        "news_type": "normal",
        "symbol": "KEX",
        "title": "BRIEF-Kirby Corp reports Q3 earnings per share $0.52 "
    },
    {
        "content": "* Kirby Corp files for resale of up to 5.7 million shares of common stock by the selling stockholders - sec filing Source text : http://bit.ly/2gnOZec Further company coverage:",
        "date": "10162017",
        "name": "Kirby Corporation",
        "news_type": "topStory",
        "symbol": "KEX",
        "title": "BRIEF-Kirby files for resale of up to 5.7 mln shares of common stock by selling stockholders "
    },
    {
        "content": "* Hushang Ansary reports 8.8 percent passive stake in Kirby Corp \u200d\u200bas of Sept 13 - SEC filing Source text: [http://bit.ly/2wgVhiB] Further company coverage:",
        "date": "09252017",
        "name": "Kirby Corporation",
        "news_type": "topStory",
        "symbol": "KEX",
        "title": "BRIEF-Hushang Ansary reports 8.8 pct passive stake in Kirby Corp "
    },
    {
        "content": "* Kirby Corporation completes the purchase of Stewart & Stevenson LLC and reports on the impact of Hurricanes Harvey and Irma",
        "date": "09132017",
        "name": "Kirby Corporation",
        "news_type": "topStory",
        "symbol": "KEX",
        "title": "BRIEF-Kirby Corp completes the purchase of Stewart & Stevenson LLC and reports on the impact of Hurricanes Harvey and Irma "
    },
    {
        "content": "* Kirby Corporation announces the resignation of executive vice president and chief financial officer C. Andrew smith",
        "date": "08172017",
        "name": "Kirby Corporation",
        "news_type": "topStory",
        "symbol": "KEX",
        "title": "BRIEF-Kirby Corporation says CFO C. Andrew Smith resigns "
    },
    {
        "content": "* Q2 revenue $473.3 million versus I/B/E/S view $481.7 million",
        "date": "07262017",
        "name": "Kirby Corporation",
        "news_type": "topStory",
        "symbol": "KEX",
        "title": "BRIEF-Kirby Corp Q2 earnings per share $0.48 "
    },
    {
        "content": "* On June 26  entered into an amendment of its existing credit agreement with a group of commercial banks - SEC filing",
        "date": "06282017",
        "name": "Kirby Corporation",
        "news_type": "topStory",
        "symbol": "KEX",
        "title": "BRIEF-Kirby Corp entered into amendment of existing credit agreement "
    },
    {
        "content": "* Kirby Corporation signs agreement to purchase inland tank barges and towboats",
        "date": "06192017",
        "name": "Kirby Corporation",
        "news_type": "topStory",
        "symbol": "KEX",
        "title": "BRIEF-Kirby Corp signs agreement to purchase inland tank barges and towboats "
    },
    {
        "content": "* Kirby corporation enters agreement to purchase stewart & stevenson llc",
        "date": "06132017",
        "name": "Kirby Corporation",
        "news_type": "topStory",
        "symbol": "KEX",
        "title": "BRIEF-Kirby Corp to buy Stewart & Stevenson LLC for about $710 mln "
    },
    {
        "content": "* Q1 earnings per share view $0.51  revenue view $425.4 million -- Thomson Reuters I/B/E/S",
        "date": "04262017",
        "name": "Kirby Corporation",
        "news_type": "topStory",
        "symbol": "KEX",
        "title": "BRIEF-Kirby Corporation sees Q2 2017 earnings per share $0.40 to $0.55 "
    },
    {
        "content": "* KIRBY CORPORATION ANNOUNCES 2016 FOURTH QUARTER AND FULL YEAR RESULTS",
        "date": "02012017",
        "name": "Kirby Corporation",
        "news_type": "topStory",
        "symbol": "KEX",
        "title": "BRIEF-KIRBY CORP Q4 EARNINGS PER SHARE $0.60 "
    },
    {
        "content": "* Baillie Gifford & Co reports 5.96 percent passive stake in Kirby Corp as of 31st December 2016 -SEC filing  Source text for Eikon:  Further company coverage:",
        "date": "01272017",
        "name": "Kirby Corporation",
        "news_type": "topStory",
        "symbol": "KEX",
        "title": "BRIEF-Baillie Gifford & Co reports 5.96 percent passive stake in Kirby Corp as of 31st Dec 2016 "
    },
    {
        "content": "* Q3 revenue $434.7 million versus I/B/E/S view $410.2 million",
        "date": "10262016",
        "name": "Kirby Corporation",
        "news_type": "topStory",
        "symbol": "KEX",
        "title": "BRIEF-Kirby Corporation announces 2016 third quarter results "
    },
    {
        "content": "United Continental Holdings Inc  has hired the No. 2 executive at rival American Airlines Group Inc   Scott Kirby  to be its president  the companies said on Monday.",
        "date": "08302016",
        "name": "Kirby Corporation",
        "news_type": "topStory",
        "symbol": "KEX",
        "title": "United Airlines hires No. 2 at American to be its president "
    },
    {
        "content": "* Expects 2016 capital spending to be unchanged in $230 to $250 million range.",
        "date": "07272016",
        "name": "Kirby Corporation",
        "news_type": "topStory",
        "symbol": "KEX",
        "title": "BRIEF-Kirby Q2 earnings per share $0.72 "
    },
    {
        "content": "* Q1 revenue $458.7 million versus i/b/e/s view $454.4 million",
        "date": "04272016",
        "name": "Kirby Corporation",
        "news_type": "topStory",
        "symbol": "KEX",
        "title": "BRIEF-Kirby Corp reports Q1 earnings per share $0.71 "
    }
]